cosmic_conn/__init__.py
cosmic_conn/data_utils.py
cosmic_conn/inference_cr.py
cosmic_conn/reduce_cr.py
cosmic_conn/train.py
cosmic_conn/cr_pipeline/__init__.py
cosmic_conn/cr_pipeline/banzai_stats.py
cosmic_conn/cr_pipeline/lco_cr_reduction.py
cosmic_conn/cr_pipeline/nres_cr_reduction.py
cosmic_conn/cr_pipeline/options.py
cosmic_conn/cr_pipeline/utils_img.py
cosmic_conn/cr_pipeline/utils_io.py
cosmic_conn/cr_pipeline/zscale.py
cosmic_conn/dl_framework/__init__.py
cosmic_conn/dl_framework/cosmic_conn.py
cosmic_conn/dl_framework/dataloader.py
cosmic_conn/dl_framework/options.py
cosmic_conn/dl_framework/parts.py
cosmic_conn/dl_framework/unet.py
cosmic_conn/dl_framework/utils_ml.py
cosmic_conn/trained_models/cosmic-conn_HST_ACS_WFC_v0.2.8.pth
cosmic_conn/trained_models/cosmic-conn_LCO_NRES_v0.2.8.pth
cosmic_conn/trained_models/cosmic-conn_ground_imaging_v0.2.8.pth
cosmic_conn/web_app/__init__.py
cosmic_conn/web_app/app.py
cosmic_conn/web_app/static/AstroMessage.js
cosmic_conn/web_app/static/ControlPanel.js
cosmic_conn/web_app/static/DownloadHandler.js
cosmic_conn/web_app/static/FileInputHandler.js
cosmic_conn/web_app/static/GlobalParas.js
cosmic_conn/web_app/static/ImageController.js
cosmic_conn/web_app/static/ImageModel.js
cosmic_conn/web_app/static/ImageUtils.js
cosmic_conn/web_app/static/ImageView.js
cosmic_conn/web_app/static/ScrollingControl.js
cosmic_conn/web_app/static/StatusIndicator.js
cosmic_conn/web_app/static/ThumbnailBar.js
cosmic_conn/web_app/static/Utils.js
cosmic_conn/web_app/static/script.js
cosmic_conn/web_app/static/css/controls.css
cosmic_conn/web_app/static/css/panel.css
cosmic_conn/web_app/static/css/splide-core.min.css
cosmic_conn/web_app/static/css/splide-default.min.css
cosmic_conn/web_app/static/css/splide.min.css
cosmic_conn/web_app/static/css/thumbnails.css
cosmic_conn/web_app/static/imgs/ImagePreview.png
cosmic_conn/web_app/static/imgs/MaskPreview.png
cosmic_conn/web_app/static/imgs/Overview.png
cosmic_conn/web_app/static/imgs/Thumbnail.png
cosmic_conn-0.4.1.dist-info/LICENSE
cosmic_conn-0.4.1.dist-info/METADATA
cosmic_conn-0.4.1.dist-info/WHEEL
cosmic_conn-0.4.1.dist-info/dependency_links.txt
cosmic_conn-0.4.1.dist-info/entry_points.txt
cosmic_conn-0.4.1.dist-info/top_level.txt
cosmic_conn-0.4.1.dist-info/RECORD
