Metadata-Version: 2.1
Name: cosmic-conn
Version: 0.4.1
Summary: Cosmic-CoNN: A Cosmic Ray Detection Deep Learning Framework, Dataset, and Toolkit
Home-page: https://github.com/cy-xu/cosmic-conn
Author: Chengyuan Xu, Curtis McCully, Boning Dong, D. Andrew Howell, and Pradeep Sen
Author-email: cxu@ucsb.edu
License: GNU General Public License v3
Keywords: cosmic_conn
Classifier: Development Status :: 3 - Alpha
Classifier: Programming Language :: Python :: 3.7
Classifier: Environment :: Console
Classifier: Environment :: Web Environment
Classifier: Environment :: GPU :: NVIDIA CUDA
Classifier: Operating System :: POSIX
Classifier: Operating System :: MacOS
Classifier: Intended Audience :: Science/Research
Classifier: License :: OSI Approved :: GNU General Public License v3 (GPLv3)
Classifier: Topic :: Scientific/Engineering :: Astronomy
Requires-Python: >=3.7
License-File: LICENSE
Requires-Dist: torch (>=1.6.0)
Requires-Dist: numpy
Requires-Dist: astropy (>=3.0)
Requires-Dist: reproject
Requires-Dist: sep
Requires-Dist: scikit-image
Requires-Dist: psutil
Requires-Dist: pretty-errors
Requires-Dist: tqdm
Requires-Dist: requests
Provides-Extra: develop
Requires-Dist: tensorboard (>=2.4.0) ; extra == 'develop'
Requires-Dist: scikit-learn (>=0.24.0) ; extra == 'develop'
Requires-Dist: Flask (>=1.1.0) ; extra == 'develop'
Requires-Dist: Flask-APScheduler (>=1.12.0) ; extra == 'develop'
Provides-Extra: webapp
Requires-Dist: Flask (>=1.1.0) ; extra == 'webapp'
Requires-Dist: Flask-APScheduler (>=1.12.0) ; extra == 'webapp'
